di_service_ksu/__init__.py
di_service_ksu/dependency_container.py
di_service_ksu/resolve_provider.py
di_service_ksu/service_collection.py
di_service_ksu/Abstractions/__init__.py
di_service_ksu/Abstractions/base_di_container.py
di_service_ksu/Abstractions/base_inject.py
di_service_ksu/Abstractions/base_service_collection.py
di_service_ksu/Abstractions/meta_inject.py
di_service_ksu/Abstractions/service_descriptor.py
di_service_ksu/Enums/__init__.py
di_service_ksu/Enums/service_life.py
di_service_ksu/Utilites/__init__.py
di_service_ksu/Utilites/ext_reflection.py
di_service_ksu-0.0.4.dist-info/METADATA
di_service_ksu-0.0.4.dist-info/WHEEL
di_service_ksu-0.0.4.dist-info/licenses/LICENSE
di_service_ksu-0.0.4.dist-info/RECORD
